glpi_api.py
lpi_api-0.3.4.dist-info/LICENSE
lpi_api-0.3.4.dist-info/METADATA
lpi_api-0.3.4.dist-info/WHEEL
lpi_api-0.3.4.dist-info/top_level.txt
lpi_api-0.3.4.dist-info/RECORD
